fractal_tasks_core/.gitignore
fractal_tasks_core/__FRACTAL_MANIFEST__.json
fractal_tasks_core/__init__.py
fractal_tasks_core/cellvoyager/__init__.py
fractal_tasks_core/cellvoyager/filenames.py
fractal_tasks_core/cellvoyager/metadata.py
fractal_tasks_core/cellvoyager/wells.py
fractal_tasks_core/channels.py
fractal_tasks_core/dev/README.md
fractal_tasks_core/dev/__init__.py
fractal_tasks_core/dev/create_manifest.py
fractal_tasks_core/dev/deprecation_message.py
fractal_tasks_core/dev/lib_args_schemas.py
fractal_tasks_core/dev/lib_descriptions.py
fractal_tasks_core/dev/lib_pydantic_generatejsonschema.py
fractal_tasks_core/dev/lib_signature_constraints.py
fractal_tasks_core/dev/lib_task_docs.py
fractal_tasks_core/dev/lib_titles.py
fractal_tasks_core/dev/task_info/apply_registration_to_image.md
fractal_tasks_core/dev/task_info/calculate_registration_image_based.md
fractal_tasks_core/dev/task_info/cellpose_segmentation.md
fractal_tasks_core/dev/task_info/convert_cellvoyager_multiplex.md
fractal_tasks_core/dev/task_info/convert_cellvoyager_to_ome_zarr.md
fractal_tasks_core/dev/task_info/find_registration_consensus.md
fractal_tasks_core/dev/task_info/illumination_correction.md
fractal_tasks_core/dev/task_info/import_ome_zarr.md
fractal_tasks_core/dev/task_info/napari_workflows_wrapper.md
fractal_tasks_core/dev/task_info/projection.md
fractal_tasks_core/dev/task_list.py
fractal_tasks_core/dev/task_models.py
fractal_tasks_core/labels.py
fractal_tasks_core/masked_loading.py
fractal_tasks_core/ngff/__init__.py
fractal_tasks_core/ngff/specs.py
fractal_tasks_core/ngff/zarr_utils.py
fractal_tasks_core/pyramids.py
fractal_tasks_core/roi/__init__.py
fractal_tasks_core/roi/_overlaps_common.py
fractal_tasks_core/roi/load_region.py
fractal_tasks_core/roi/v1.py
fractal_tasks_core/roi/v1_checks.py
fractal_tasks_core/roi/v1_overlaps.py
fractal_tasks_core/tables/__init__.py
fractal_tasks_core/tables/v1.py
fractal_tasks_core/tasks/__init__.py
fractal_tasks_core/tasks/_registration_utils.py
fractal_tasks_core-1.5.4.dist-info/LICENSE
fractal_tasks_core-1.5.4.dist-info/METADATA
fractal_tasks_core-1.5.4.dist-info/WHEEL
fractal_tasks_core-1.5.4.dist-info/RECORD
