Metadata-Version: 2.1
Name: fractal-tasks-core
Version: 1.5.4
Summary: Core bioimage-analysis library and tasks of the Fractal analytics platform
Home-page: https://github.com/fractal-analytics-platform/fractal-tasks-core
License: BSD-3-Clause
Author: Joel Lüthi 
Author-email: joel.luethi@fmi.ch
Requires-Python: >=3.11,<3.13
Classifier: License :: OSI Approved :: BSD License
Classifier: Programming Language :: Python :: 3
Classifier: Programming Language :: Python :: 3.11
Classifier: Programming Language :: Python :: 3.12
Provides-Extra: fractal-tasks
Requires-Dist: Pillow (>=9.1.1) ; extra == "fractal-tasks"
Requires-Dist: anndata (>=0.8.0,<0.11.0)
Requires-Dist: cellpose (>=2.2,<2.3) ; extra == "fractal-tasks"
Requires-Dist: dask (>=2023.1.0)
Requires-Dist: docstring-parser (>=0.15.0,<=0.16.0)
Requires-Dist: filelock (==3.13.*)
Requires-Dist: fractal-task-tools (==0.0.12)
Requires-Dist: fsspec (!=2023.9.0)
Requires-Dist: image_registration (>=0.2.9) ; extra == "fractal-tasks"
Requires-Dist: imageio-ffmpeg (>=0.4.7,<0.5.0) ; extra == "fractal-tasks"
Requires-Dist: lxml (<=5.4.0)
Requires-Dist: napari-segment-blobs-and-things-with-membranes (>=0.3.3,<0.4.0) ; extra == "fractal-tasks"
Requires-Dist: napari-skimage-regionprops (>=0.8.1,<0.9.0) ; extra == "fractal-tasks"
Requires-Dist: napari-tools-menu (>=0.1.19,<0.2.0) ; extra == "fractal-tasks"
Requires-Dist: napari-workflows (>=0.2.8,<0.3.0) ; extra == "fractal-tasks"
Requires-Dist: ngio (>=0.2.4,<0.3.0)
Requires-Dist: numcodecs (<0.16.0)
Requires-Dist: numpy (<=2.1.0)
Requires-Dist: pandas (>=1.2.0)
Requires-Dist: pydantic (>2,<=2.8.2)
Requires-Dist: scikit-image (>=0.19) ; extra == "fractal-tasks"
Requires-Dist: stackview (<0.9.0) ; extra == "fractal-tasks"
Requires-Dist: torch (<=3.0.0) ; extra == "fractal-tasks"
Requires-Dist: zarr (>=2.13.6,<3)
Project-URL: Changelog, https://github.com/fractal-analytics-platform/fractal-tasks-core/blob/main/CHANGELOG.md
Project-URL: Documentation, https://fractal-analytics-platform.github.io/fractal-tasks-core
Project-URL: Repository, https://github.com/fractal-analytics-platform/fractal-tasks-core
